README.md
setup.py
hapool/__init__.py
hapool/__version__.py
hapool/decorators.py
hapool/exceptions.py
hapool/ha_algorithm.py
hapool/ha_endpoint_pool.py
hapool.egg-info/PKG-INFO
hapool.egg-info/SOURCES.txt
hapool.egg-info/dependency_links.txt
hapool.egg-info/requires.txt
hapool.egg-info/top_level.txt