Metadata-Version: 2.1
Name: hapool
Version: 0.0.1
Summary: A handy, customizable python library that provides high availability for multiple node connections
Home-page: https://github.com/IMBlues/pyhapool
Author: Amazing Blues
Author-email: bluesedenyu@gmail.com
License: MIT
Platform: UNKNOWN
Classifier: License :: OSI Approved :: MIT License
Classifier: Programming Language :: Python
Classifier: Programming Language :: Python :: 3
Classifier: Programming Language :: Python :: 3.6
Classifier: Programming Language :: Python :: Implementation :: CPython
Classifier: Programming Language :: Python :: Implementation :: PyPy
Requires-Python: >=3.6.0
